pybotters/__init__.py
pybotters/__version__.py
pybotters/auth.py
pybotters/client.py
pybotters/py.typed
pybotters/request.py
pybotters/store.py
pybotters/typedefs.py
pybotters/ws.py
pybotters/_static_dependencies/__init__.py
pybotters/_static_dependencies/ecdsa/__init__.py
pybotters/_static_dependencies/ecdsa/_version.py
pybotters/_static_dependencies/ecdsa/curves.py
pybotters/_static_dependencies/ecdsa/der.py
pybotters/_static_dependencies/ecdsa/ecdsa.py
pybotters/_static_dependencies/ecdsa/ellipticcurve.py
pybotters/_static_dependencies/ecdsa/keys.py
pybotters/_static_dependencies/ecdsa/numbertheory.py
pybotters/_static_dependencies/ecdsa/rfc6979.py
pybotters/_static_dependencies/ecdsa/util.py
pybotters/_static_dependencies/ethereum/__init__.py
pybotters/_static_dependencies/ethereum/abi/__init__.py
pybotters/_static_dependencies/ethereum/abi/abi.py
pybotters/_static_dependencies/ethereum/abi/base.py
pybotters/_static_dependencies/ethereum/abi/codec.py
pybotters/_static_dependencies/ethereum/abi/constants.py
pybotters/_static_dependencies/ethereum/abi/decoding.py
pybotters/_static_dependencies/ethereum/abi/encoding.py
pybotters/_static_dependencies/ethereum/abi/exceptions.py
pybotters/_static_dependencies/ethereum/abi/grammar.py
pybotters/_static_dependencies/ethereum/abi/packed.py
pybotters/_static_dependencies/ethereum/abi/py.typed
pybotters/_static_dependencies/ethereum/abi/registry.py
pybotters/_static_dependencies/ethereum/abi/tools/__init__.py
pybotters/_static_dependencies/ethereum/abi/tools/_strategies.py
pybotters/_static_dependencies/ethereum/abi/utils/__init__.py
pybotters/_static_dependencies/ethereum/abi/utils/numeric.py
pybotters/_static_dependencies/ethereum/abi/utils/padding.py
pybotters/_static_dependencies/ethereum/abi/utils/string.py
pybotters/_static_dependencies/ethereum/account/__init__.py
pybotters/_static_dependencies/ethereum/account/messages.py
pybotters/_static_dependencies/ethereum/account/py.typed
pybotters-1.9.1.dist-info/METADATA
pybotters-1.9.1.dist-info/WHEEL
pybotters-1.9.1.dist-info/licenses/LICENCE
pybotters-1.9.1.dist-info/RECORD
