Metadata-Version: 2.4
Name: pybotters
Version: 1.9.1
Summary: An advanced API client for python crypto bot traders
Project-URL: Documentation, https://pybotters.readthedocs.io/ja/stable/
Project-URL: Repository, https://github.com/pybotters/pybotters
Author-email: MtkN1 <51289448+MtkN1@users.noreply.github.com>
License-Expression: MIT
License-File: LICENCE
Keywords: aiohttp,crypto,exchange,trading
Classifier: Development Status :: 5 - Production/Stable
Classifier: Framework :: AsyncIO
Classifier: Framework :: aiohttp
Classifier: Intended Audience :: Developers
Classifier: Intended Audience :: Financial and Insurance Industry
Classifier: License :: OSI Approved :: MIT License
Classifier: Natural Language :: Japanese
Classifier: Operating System :: MacOS :: MacOS X
Classifier: Operating System :: Microsoft :: Windows
Classifier: Operating System :: POSIX
Classifier: Programming Language :: Python
Classifier: Programming Language :: Python :: 3
Classifier: Programming Language :: Python :: 3.9
Classifier: Programming Language :: Python :: 3.10
Classifier: Programming Language :: Python :: 3.11
Classifier: Programming Language :: Python :: 3.12
Classifier: Programming Language :: Python :: 3.13
Classifier: Topic :: Internet :: WWW/HTTP
Classifier: Topic :: Office/Business :: Financial :: Investment
Classifier: Typing :: Typed
Requires-Python: >=3.9
Requires-Dist: aiohttp>=3.7
Requires-Dist: typing-extensions>=3.10; python_version < '3.10'
